{
  "ablation": "no_efficiency",
  "description": "Remove efficiency guidance signal",
  "config": {
    "description": "Remove efficiency guidance signal",
    "use_guidance": true,
    "active_signals": [
      "task",
      "safety",
      "coordination"
    ],
    "guidance_scale": 3.0
  },
  "metrics": {
    "task_success_rate": 0.4,
    "action_efficiency": 2.021912219187761,
    "coordination_score": -2.9850172746929706,
    "avg_turn_count": 12.44,
    "delegation_accuracy": 1.0,
    "avg_bertscore": 0.0,
    "avg_coherence": 0.0,
    "functional_fluency_gap": 0.4,
    "num_episodes": 50,
    "simple/task_success_rate": 0.16666666666666666,
    "simple/action_efficiency": 0.6445246111912778,
    "simple/coordination_score": -0.7098084014750681,
    "simple/avg_turn_count": 8.38888888888889,
    "simple/num_episodes": 18,
    "moderate/task_success_rate": 0.375,
    "moderate/action_efficiency": 1.3414995543672013,
    "moderate/coordination_score": -2.072396297534165,
    "moderate/avg_turn_count": 14.875,
    "moderate/num_episodes": 16,
    "complex/task_success_rate": 0.6875,
    "complex/action_efficiency": 4.251885943004364,
    "complex/coordination_score": -6.457248234221918,
    "complex/avg_turn_count": 14.5625,
    "complex/num_episodes": 16
  },
  "gen_time_mean": 0.8083808660507202,
  "gen_time_std": 0.002388097831465254,
  "elapsed_s": 64.45786619186401,
  "num_episodes": 50,
  "sample_dialogues": {
    "t001": [
      "Alright, I'm heading to room_3, the bedroom is looking tidy!",
      "Okay, so I'm moving to room_2.",
      "Alright, I'm heading to room_3, the studyy!",
      "Alright, I's all set now."
    ],
    "t002": [
      "Alright, I'm heading to room_0.",
      "Alright, I'm heading to room_3, the studyy!",
      "Alright, I'm heading around, room_0 looks!",
      "Alo, I'm in the place as I know what to do next."
    ],
    "t003": [
      "Yeah, I'm not seeing anything in here.",
      "Alright, I'm heading to room_3, the studyy.",
      "Alright, I'm heading to room_3, everything looks out of the place.",
      "Okay, so I've found the red mug..."
    ]
  }
}